README
setup.py
sqlexecutor/__init__.py
sqlexecutor/mysqlexecutor.py
sqlexecutor/results.py
sqlexecutor/tempdir.py
sqlexecutor.egg-info/PKG-INFO
sqlexecutor.egg-info/SOURCES.txt
sqlexecutor.egg-info/dependency_links.txt
sqlexecutor.egg-info/requires.txt
sqlexecutor.egg-info/top_level.txt