Metadata-Version: 1.0
Name: sqlexecutor
Version: 0.1.1
Summary: Execute SQL queries in an isolated database
Home-page: http://github.com/mwilliamson/sqlexecutor
Author: Michael Williamson
Author-email: UNKNOWN
License: BSD 2-Clause
Platform: UNKNOWN
